protoblade/__main__.py
protoblade/blade.py
protoblade/cad.py
protoblade/cli.py
protoblade/geom.py
protoblade/machine.py
protoblade/stage.py
protoblade-0.2.0.dist-info/LICENSE
protoblade-0.2.0.dist-info/METADATA
protoblade-0.2.0.dist-info/WHEEL
protoblade-0.2.0.dist-info/RECORD
