Metadata-Version: 2.1
Name: protoblade
Version: 0.2.0
Summary: 
License: Apache Software Licence
Author: Tesseract Software
Requires-Python: >=3.8
Classifier: License :: Other/Proprietary License
Classifier: Programming Language :: Python :: 3
Classifier: Programming Language :: Python :: 3.8
Classifier: Programming Language :: Python :: 3.9
Classifier: Programming Language :: Python :: 3.10
Classifier: Programming Language :: Python :: 3.11
Classifier: Programming Language :: Python :: 3.12
Requires-Dist: atom (>=0.10,<0.11)
Requires-Dist: cadquery (>=2.4,<3.0)
Requires-Dist: numpy (>=1.24,<2.0)
Requires-Dist: scipy (>=1,<2)
Requires-Dist: tomli (>=2,<3)
Requires-Dist: tomli_w (>=1,<2)
Requires-Dist: tomlkit (>=0.13,<0.14)
